enelvo/__init__.py
enelvo/__main__.py
enelvo/analytics.py
enelvo/candidate_generation/__init__.py
enelvo/candidate_generation/baselines.py
enelvo/candidate_generation/embeddings.py
enelvo/candidate_scoring/__init__.py
enelvo/candidate_scoring/baselines.py
enelvo/candidate_scoring/embeddings.py
enelvo/log.py
enelvo/metrics/__init__.py
enelvo/metrics/enelvo/metrics/cythonlcs.cpython-36m-darwin.so
enelvo/metrics/metrics.py
enelvo/normaliser.py
enelvo/preprocessing/__init__.py
enelvo/preprocessing/preprocessing.py
enelvo/preprocessing/tokenizer/__init__.py
enelvo/preprocessing/tokenizer/lexicons/domains.txt
enelvo/preprocessing/tokenizer/lexicons/emoticons.txt
enelvo/preprocessing/tokenizer/lexicons/stopwords.txt
enelvo/preprocessing/tokenizer/tokenizer.py
enelvo/resources/corr-lexicons/acs.txt
enelvo/resources/corr-lexicons/es.txt
enelvo/resources/corr-lexicons/in.txt
enelvo/resources/corr-lexicons/pns.txt
enelvo/resources/embeddings/README
enelvo/resources/embeddings/norm_lexicon.pickle
enelvo/resources/lexicons/README
enelvo/resources/lexicons/english-5k.txt
enelvo/resources/lexicons/freq-cgu.txt
enelvo/resources/lexicons/lex-ugcnormal-cb100.txt
enelvo/resources/lexicons/unitex-full-clean+enelvo-ja-corrigido.txt
enelvo/run.py
enelvo/sanitize.txt
enelvo/utils/__init__.py
enelvo/utils/evaluation.py
enelvo/utils/loaders.py
enelvo-0.15.dist-info/LICENSE
enelvo-0.15.dist-info/METADATA
enelvo-0.15.dist-info/WHEEL
enelvo-0.15.dist-info/RECORD
