Metadata-Version: 2.1
Name: enelvo
Version: 0.15
Summary: A flexible normalizer for user-generated content http://thalesbertaglia.com/enelvo
Home-page: https://github.com/thalesbertaglia/enelvo
License: MIT
Author: Thales Bertaglia
Author-email: contact@thalesbertaglia.com
Requires-Python: >=3.6
Classifier: License :: OSI Approved :: MIT License
Classifier: Programming Language :: Python :: 3
Classifier: Programming Language :: Python :: 3.6
Classifier: Programming Language :: Python :: 3.7
Classifier: Programming Language :: Python :: 3.8
Classifier: Programming Language :: Python :: 3.9
Classifier: Programming Language :: Python :: 3.10
Classifier: Programming Language :: Python :: 3.11
Requires-Dist: editdistance (>=0.6.0)
Requires-Dist: emoji (==2.2.0)
Requires-Dist: gensim (>=4.1.2)
Requires-Dist: numpy (>=1.19.5)
Requires-Dist: tabulate (>=0.8.9)
Project-URL: Repository, https://github.com/thalesbertaglia/enelvo
